{
  "timestamp": "2025-12-19T06:47:27.792Z",
  "overall": "failed",
  "summary": {
    "total": 9,
    "passed": 5,
    "failed": 1,
    "skipped": 3
  },
  "stages": [
    {
      "name": "connection",
      "status": "passed",
      "duration": 3082
    },
    {
      "name": "health",
      "status": "passed",
      "duration": 928
    },
    {
      "name": "auth",
      "status": "passed",
      "duration": 1439
    },
    {
      "name": "bucket-create",
      "status": "passed",
      "duration": 24177
    },
    {
      "name": "storage-request",
      "status": "passed",
      "duration": 33965
    },
    {
      "name": "file-upload",
      "status": "failed",
      "duration": 675840,
      "error": "Timeout waiting for StorageRequestFulfilled"
    },
    {
      "name": "file-download",
      "status": "skipped",
      "duration": 0
    },
    {
      "name": "file-delete",
      "status": "skipped",
      "duration": 0
    },
    {
      "name": "bucket-delete",
      "status": "skipped",
      "duration": 0
    }
  ]
}