{
  "timestamp": "2026-01-18T10:06:21.995Z",
  "overall": "failed",
  "summary": {
    "total": 9,
    "passed": 5,
    "failed": 1,
    "skipped": 3
  },
  "stages": [
    {
      "name": "connection",
      "status": "passed",
      "duration": 3092
    },
    {
      "name": "health",
      "status": "passed",
      "duration": 638
    },
    {
      "name": "auth",
      "status": "passed",
      "duration": 830
    },
    {
      "name": "bucket-create",
      "status": "passed",
      "duration": 24938
    },
    {
      "name": "storage-request",
      "status": "passed",
      "duration": 33834
    },
    {
      "name": "file-upload",
      "status": "failed",
      "duration": 675884,
      "error": "Timeout waiting for StorageRequestFulfilled"
    },
    {
      "name": "file-download",
      "status": "skipped",
      "duration": 0
    },
    {
      "name": "file-delete",
      "status": "skipped",
      "duration": 0
    },
    {
      "name": "bucket-delete",
      "status": "skipped",
      "duration": 0
    }
  ]
}