{
  "timestamp": "2026-01-05T07:57:13.765Z",
  "overall": "success",
  "summary": {
    "total": 9,
    "passed": 9,
    "failed": 0,
    "skipped": 0
  },
  "stages": [
    {
      "name": "connection",
      "status": "passed",
      "duration": 2189
    },
    {
      "name": "health",
      "status": "passed",
      "duration": 571
    },
    {
      "name": "auth",
      "status": "passed",
      "duration": 703
    },
    {
      "name": "bucket-create",
      "status": "passed",
      "duration": 24009
    },
    {
      "name": "storage-request",
      "status": "passed",
      "duration": 34013
    },
    {
      "name": "file-upload",
      "status": "passed",
      "duration": 38554
    },
    {
      "name": "file-download",
      "status": "passed",
      "duration": 611
    },
    {
      "name": "file-delete",
      "status": "passed",
      "duration": 341054
    },
    {
      "name": "bucket-delete",
      "status": "passed",
      "duration": 35864
    }
  ]
}