{
  "timestamp": "2026-01-03T04:53:25.730Z",
  "overall": "success",
  "summary": {
    "total": 9,
    "passed": 9,
    "failed": 0,
    "skipped": 0
  },
  "stages": [
    {
      "name": "connection",
      "status": "passed",
      "duration": 2553
    },
    {
      "name": "health",
      "status": "passed",
      "duration": 567
    },
    {
      "name": "auth",
      "status": "passed",
      "duration": 896
    },
    {
      "name": "bucket-create",
      "status": "passed",
      "duration": 23903
    },
    {
      "name": "storage-request",
      "status": "passed",
      "duration": 34026
    },
    {
      "name": "file-upload",
      "status": "passed",
      "duration": 38597
    },
    {
      "name": "file-download",
      "status": "passed",
      "duration": 591
    },
    {
      "name": "file-delete",
      "status": "passed",
      "duration": 340964
    },
    {
      "name": "bucket-delete",
      "status": "passed",
      "duration": 35987
    }
  ]
}