{
  "timestamp": "2025-12-15T03:47:01.751Z",
  "overall": "success",
  "summary": {
    "total": 9,
    "passed": 9,
    "failed": 0,
    "skipped": 0
  },
  "stages": [
    {
      "name": "connection",
      "status": "passed",
      "duration": 1623
    },
    {
      "name": "health",
      "status": "passed",
      "duration": 354
    },
    {
      "name": "auth",
      "status": "passed",
      "duration": 611
    },
    {
      "name": "bucket-create",
      "status": "passed",
      "duration": 25911
    },
    {
      "name": "storage-request",
      "status": "passed",
      "duration": 34025
    },
    {
      "name": "file-upload",
      "status": "passed",
      "duration": 38497
    },
    {
      "name": "file-download",
      "status": "passed",
      "duration": 538
    },
    {
      "name": "file-delete",
      "status": "passed",
      "duration": 65032
    },
    {
      "name": "bucket-delete",
      "status": "passed",
      "duration": 35920
    }
  ]
}