{
  "timestamp": "2026-01-17T06:07:02.764Z",
  "overall": "failed",
  "summary": {
    "total": 9,
    "passed": 5,
    "failed": 1,
    "skipped": 3
  },
  "stages": [
    {
      "name": "connection",
      "status": "passed",
      "duration": 2218
    },
    {
      "name": "health",
      "status": "passed",
      "duration": 588
    },
    {
      "name": "auth",
      "status": "passed",
      "duration": 733
    },
    {
      "name": "bucket-create",
      "status": "passed",
      "duration": 23707
    },
    {
      "name": "storage-request",
      "status": "passed",
      "duration": 32647
    },
    {
      "name": "file-upload",
      "status": "failed",
      "duration": 675817,
      "error": "Timeout waiting for StorageRequestFulfilled"
    },
    {
      "name": "file-download",
      "status": "skipped",
      "duration": 0
    },
    {
      "name": "file-delete",
      "status": "skipped",
      "duration": 0
    },
    {
      "name": "bucket-delete",
      "status": "skipped",
      "duration": 0
    }
  ]
}