{
  "timestamp": "2025-12-27T09:24:39.799Z",
  "overall": "failed",
  "summary": {
    "total": 9,
    "passed": 5,
    "failed": 1,
    "skipped": 3
  },
  "stages": [
    {
      "name": "connection",
      "status": "passed",
      "duration": 2894
    },
    {
      "name": "health",
      "status": "passed",
      "duration": 579
    },
    {
      "name": "auth",
      "status": "passed",
      "duration": 720
    },
    {
      "name": "bucket-create",
      "status": "passed",
      "duration": 21105
    },
    {
      "name": "storage-request",
      "status": "passed",
      "duration": 33995
    },
    {
      "name": "file-upload",
      "status": "failed",
      "duration": 57759,
      "error": "HTTP 400 for PUT https://deo-dh-backend.testnet.datahaven-infra.network/buckets/0x0bfcc5b964a8be9ee6417346c45d6d4f6b15636f01df51d1568f6c0ec626d22a/upload/0xbe9e8b675701af0722c695ec913c286d55e3208d96c7d5d4b4abab4cd66f61eb"
    },
    {
      "name": "file-download",
      "status": "skipped",
      "duration": 0
    },
    {
      "name": "file-delete",
      "status": "skipped",
      "duration": 0
    },
    {
      "name": "bucket-delete",
      "status": "skipped",
      "duration": 0
    }
  ]
}